appixer/metadata/__init__.py
appixer/metadata/flac.py
appixer/metadata/mp3.py
appixer/metadata/music.py
appixer/metadata/utils.py
appixer_metadata-1.0.2.dist-info/LICENSE
appixer_metadata-1.0.2.dist-info/METADATA
appixer_metadata-1.0.2.dist-info/WHEEL
appixer_metadata-1.0.2.dist-info/top_level.txt
appixer_metadata-1.0.2.dist-info/RECORD
